win32_gui_utils/__init__.py
win32_gui_utils/win32_gui_utils.py
win32_gui_utils-0.0.3.dist-info/LICENSE
win32_gui_utils-0.0.3.dist-info/METADATA
win32_gui_utils-0.0.3.dist-info/WHEEL
win32_gui_utils-0.0.3.dist-info/top_level.txt
win32_gui_utils-0.0.3.dist-info/RECORD
