Metadata-Version: 2.2
Name: win32_gui_utils
Version: 0.0.3
Summary: Uma biblioteca para automação de controles GUI.
Author: Leonardo Almeida
Author-email: leonardoti.dev@gmail.com
Classifier: Programming Language :: Python :: 3
Classifier: Operating System :: Microsoft :: Windows
Classifier: License :: OSI Approved :: MIT License
Requires-Python: >=3.6
License-File: LICENSE
Requires-Dist: pywin32
Dynamic: author
Dynamic: author-email
Dynamic: classifier
Dynamic: description
Dynamic: description-content-type
Dynamic: requires-dist
Dynamic: requires-python
Dynamic: summary
